MANIFEST.in
README.md
requirements.txt
setup.py
coolkit/__init__.py
coolkit/main.py
coolkit.egg-info/PKG-INFO
coolkit.egg-info/SOURCES.txt
coolkit.egg-info/dependency_links.txt
coolkit.egg-info/entry_points.txt
coolkit.egg-info/requires.txt
coolkit.egg-info/top_level.txt
coolkit/dependencies/__init__.py
coolkit/dependencies/__init__.pyc
coolkit/dependencies/dependencies.py
coolkit/dependencies/dependencies.pyc
coolkit/dependencies/dependency.py
coolkit/dependencies/dependency.pyc
coolkit/extra/__init__.py
coolkit/extra/global_config.py
coolkit/lib/Args.py
coolkit/lib/Colour.py
coolkit/lib/Constants.py
coolkit/lib/Contest.py
coolkit/lib/Friends.py
coolkit/lib/Parser.py
coolkit/lib/Problem.py
coolkit/lib/Profile.py
coolkit/lib/Runner.py
coolkit/lib/Submit.py
coolkit/lib/__init__.py
coolkit/lib/add_friends.py
coolkit/lib/global_config.py
coolkit/lib/srbjson.py
coolkit/lib/utils.py
test/__init__.py