Metadata-Version: 2.1
Name: coolkit
Version: 0.0.9
Summary: A command line tool for competitive programming
Home-page: http://github.com/srbcheema1/CoolKit
Author: Sarbjit Singh
Author-email: srbcheema1@gmail.com
License: MIT License
Platform: UNKNOWN
Classifier: Operating System :: POSIX :: Linux
Classifier: License :: OSI Approved :: MIT License
Classifier: Programming Language :: Python :: 3.5
